<?xml version="1.1" encoding="UTF-8" standalone="no"?>
<databaseChangeLog xmlns="http://www.liquibase.org/xml/ns/dbchangelog"
                   xmlns:ext="http://www.liquibase.org/xml/ns/dbchangelog-ext"
                   xmlns:pro="http://www.liquibase.org/xml/ns/pro"
                   xmlns:xsi="http://www.w3.org/2001/XMLSchema-instance"
                   xsi:schemaLocation="http://www.liquibase.org/xml/ns/dbchangelog dbchangelog.xsd
    http://www.liquibase.org/xml/ns/dbchangelog-ext dbchangelog.xsd
    http://www.liquibase.org/xml/ns/pro dbchangelog.xsd" >
    <property name="utilityModule" value="(SELECT id FROM module WHERE name = 'utility')"/>
    <property name="customCommandFeature" value="(SELECT id FROM feature WHERE key = 'customCommand')"/>

    <changeSet  author="Sheldan"  id="customCommand-commands">
        <insert tableName="command">
            <column name="name" value="createCustomCommand"/>
            <column name="module_id" valueComputed="${utilityModule}"/>
            <column name="feature_id" valueComputed="${customCommandFeature}"/>
        </insert>
        <insert tableName="command">
            <column name="name" value="deleteCustomCommand"/>
            <column name="module_id" valueComputed="${utilityModule}"/>
            <column name="feature_id" valueComputed="${customCommandFeature}"/>
        </insert>
        <insert tableName="command">
            <column name="name" value="getCustomCommand"/>
            <column name="module_id" valueComputed="${utilityModule}"/>
            <column name="feature_id" valueComputed="${customCommandFeature}"/>
        </insert>
        <insert tableName="command">
            <column name="name" value="listCustomCommands"/>
            <column name="module_id" valueComputed="${utilityModule}"/>
            <column name="feature_id" valueComputed="${customCommandFeature}"/>
        </insert>
    </changeSet>

</databaseChangeLog>